simos/__init__.py
simos/coherent.py
simos/core.py
simos/fast_expm.py
simos/fokker.py
simos/incoherent.py
simos/propagation.py
simos/qmatrixmethods.py
simos/spherical.py
simos/states.py
simos/trivial.py
simos/backends/__init__.py
simos/backends/numpy.py
simos/backends/qutip.py
simos/backends/sparse.py
simos/backends/sympy.py
simos/constants/__init__.py
simos/constants/gyromagnetic_ratios.py
simos/systems/NV.py
simos/systems/SCRP.py
simos/systems/__init__.py
simos/utils/__init__.py
simos/utils/exporter.py
simos/utils/fitfuncs.py
simos/utils/jupyter_helper.py
simos/utils/process.py
simos-0.2.3.dist-info/licenses/LICENSE
simos-0.2.3.dist-info/METADATA
simos-0.2.3.dist-info/WHEEL
simos-0.2.3.dist-info/top_level.txt
simos-0.2.3.dist-info/RECORD
