Metadata-Version: 2.4
Name: simos
Version: 0.2.3
Summary: Spin simulations in Python (NMR, EPR/ESR as well as ODMR).
Home-page: https://simos.kherb.io
Author: Konstantin Herb
Author-email: science@rashbw.de
License: GNU Lesser General Public License v3 or later (LGPLv3+)
Platform: any
Classifier: Development Status :: 3 - Alpha
Classifier: Environment :: GPU
Classifier: Intended Audience :: Science/Research
Classifier: Intended Audience :: Developers
Classifier: License :: OSI Approved :: GNU Lesser General Public License v3 or later (LGPLv3+)
Classifier: Operating System :: Microsoft :: Windows
Classifier: Operating System :: MacOS
Classifier: Operating System :: POSIX
Classifier: Operating System :: Unix
Classifier: Operating System :: OS Independent
Classifier: Programming Language :: Python :: 3
Classifier: Programming Language :: Python :: 3.9
Classifier: Programming Language :: Python :: 3.10
Classifier: Programming Language :: Python :: 3.11
Classifier: Programming Language :: Python :: 3.12
Classifier: Topic :: Education
Classifier: Topic :: Scientific/Engineering
Classifier: Topic :: Scientific/Engineering :: Physics
Classifier: Topic :: Scientific/Engineering :: Chemistry
License-File: LICENSE
Requires-Dist: numpy>=1.25.0
Requires-Dist: scipy>=1.12.0
Provides-Extra: recommended
Requires-Dist: qutip>=5.0.0; extra == "recommended"
Requires-Dist: sympy>=1.11; extra == "recommended"
Requires-Dist: matplotlib; extra == "recommended"
Requires-Dist: IPython; extra == "recommended"
Provides-Extra: full
Requires-Dist: qutip; extra == "full"
Requires-Dist: sympy; extra == "full"
Requires-Dist: matplotlib; extra == "full"
Requires-Dist: numba>=0.58.0; extra == "full"
Requires-Dist: IPython; extra == "full"
Requires-Dist: tkinter; extra == "full"
Provides-Extra: docs
Requires-Dist: sphinx; extra == "docs"
Requires-Dist: sphinx_rtd_theme; extra == "docs"
Requires-Dist: simos[recommended]; extra == "docs"
Requires-Dist: sphinx-exec-code; extra == "docs"
Provides-Extra: test
Requires-Dist: pytest; extra == "test"
Requires-Dist: pytest-cov; extra == "test"
Requires-Dist: simos[full]; extra == "test"
Dynamic: author
Dynamic: author-email
Dynamic: classifier
Dynamic: description
Dynamic: description-content-type
Dynamic: home-page
Dynamic: license
Dynamic: license-file
Dynamic: platform
Dynamic: provides-extra
Dynamic: requires-dist
Dynamic: summary
